proalgotrader_strategy_runner/__init__.py
proalgotrader_strategy_runner/main.py
proalgotrader_strategy_runner-0.1.0.dist-info/METADATA
proalgotrader_strategy_runner-0.1.0.dist-info/WHEEL
proalgotrader_strategy_runner-0.1.0.dist-info/top_level.txt
proalgotrader_strategy_runner-0.1.0.dist-info/RECORD
