Metadata-Version: 2.1
Name: proalgotrader-strategy-runner
Version: 0.1.0
Summary: ProAlgoTrader Strategy Runner
Home-page: https://github.com/krunaldodiya/proalgotrader_strategy_runner
Author: Krunal Dodiya
Author-email: kunal.dodiya1@gmail.com
Classifier: Programming Language :: Python :: 3
Classifier: Operating System :: OS Independent
Requires-Dist: fastapi
Requires-Dist: apscheduler
